streaming_left_join.py
streaming_left_join-0.0.7.dist-info/LICENSE
streaming_left_join-0.0.7.dist-info/METADATA
streaming_left_join-0.0.7.dist-info/WHEEL
streaming_left_join-0.0.7.dist-info/top_level.txt
streaming_left_join-0.0.7.dist-info/RECORD
