Metadata-Version: 2.1
Name: streaming-left-join
Version: 0.0.7
Summary: Join iterables in code without loading them all in memory: similar to a SQL left join.
Home-page: https://github.com/uktrade/python-streaming-left-join
Author: Department for International Trade
Author-email: webops@digital.trade.gov.uk
License: UNKNOWN
Platform: UNKNOWN
Classifier: Programming Language :: Python :: 3
Classifier: License :: OSI Approved :: MIT License
Classifier: Operating System :: OS Independent
Requires-Python: >=3.6.3
